traceai_pipecat/__init__.py
traceai_pipecat/exporters/__init__.py
traceai_pipecat/exporters/base_exporter.py
traceai_pipecat/exporters/grpc_exporter.py
traceai_pipecat/exporters/http_exporter.py
traceai_pipecat/integration.py
traceai_pipecat/version.py
traceai_pipecat-0.1.0.dist-info/METADATA
traceai_pipecat-0.1.0.dist-info/WHEEL
traceai_pipecat-0.1.0.dist-info/RECORD
